karton/core/__init__.py
karton/core/__version__.py
karton/core/backend.py
karton/core/base.py
karton/core/config.py
karton/core/exceptions.py
karton/core/inspect.py
karton/core/karton.py
karton/core/logger.py
karton/core/main.py
karton/core/py.typed
karton/core/query.py
karton/core/resource.py
karton/core/task.py
karton/core/test.py
karton/core/utils.py
karton/core/asyncio/__init__.py
karton/core/asyncio/backend.py
karton/core/asyncio/base.py
karton/core/asyncio/karton.py
karton/core/asyncio/logger.py
karton/core/asyncio/resource.py
karton/system/__init__.py
karton/system/__main__.py
karton/system/system.py
karton_core-5.9.0.dist-info/licenses/LICENSE
karton_core-5.9.0.dist-info/METADATA
karton_core-5.9.0.dist-info/WHEEL
karton_core-5.9.0.dist-info/entry_points.txt
karton_core-5.9.0.dist-info/top_level.txt
karton_core-5.9.0.dist-info/RECORD
