Metadata-Version: 2.4
Name: karton-core
Version: 5.9.0
Summary: Distributed malware analysis orchestration framework
License-Expression: BSD-3-Clause
Project-URL: Homepage, https://github.com/CERT-Polska/karton
Project-URL: Documentation, https://karton-core.readthedocs.io/
Project-URL: Repository, https://github.com/CERT-Polska/karton
Classifier: Programming Language :: Python :: 3
Classifier: Operating System :: OS Independent
Requires-Python: >=3.8
License-File: LICENSE
Requires-Dist: redis
Requires-Dist: orjson
Requires-Dist: boto3<=1.35.81
Requires-Dist: aioboto3==13.3.0
Dynamic: license-file
